neozot/__main__.py
neozot/feedprovider.py
neozot/recommender.py
neozot/ssrec.py
neozot/zoterodb.py
neozot/ui/index.html
neozot/ui/style.css
neozot-0.0.5.dist-info/LICENSE
neozot-0.0.5.dist-info/METADATA
neozot-0.0.5.dist-info/WHEEL
neozot-0.0.5.dist-info/top_level.txt
neozot-0.0.5.dist-info/RECORD
