Metadata-Version: 2.1
Name: neozot
Version: 0.0.5
Summary: neozot
Home-page: https://github.com/v-i-s-h/neozot-py/
Author: Vishnu Raj
Author-email: rajvishnu@duck.com
Keywords: zotero,arxiv,research
Classifier: Development Status :: 3 - Alpha
Classifier: Natural Language :: English
Classifier: Operating System :: MacOS
Classifier: Operating System :: POSIX
Classifier: Operating System :: Microsoft :: Windows :: Windows 10
Classifier: Programming Language :: Python :: 3
Classifier: Programming Language :: Python :: 3.7
Classifier: Programming Language :: Python :: 3.8
Classifier: Programming Language :: Python :: 3.9
Classifier: Programming Language :: Python :: Implementation :: CPython
Classifier: License :: OSI Approved :: MIT License
Requires-Python: >=3.7
License-File: LICENSE
Requires-Dist: appdirs
Requires-Dist: eel
Requires-Dist: numpy
Requires-Dist: requests
Requires-Dist: scikit-learn
